click_conf_file/__init__.py
click_conf_file/decorator.py
click_conf_file-0.2.0.dist-info/WHEEL
click_conf_file-0.2.0.dist-info/METADATA
click_conf_file-0.2.0.dist-info/RECORD
